py2saber/__init__.py
py2saber/__main__.py
py2saber/py2saber.py
py2saber/OpenCore_OEM/BEEP.RAW
py2saber/OpenCore_OEM/CLASH_10_0.RAW
py2saber/OpenCore_OEM/CLASH_1_0.RAW
py2saber/OpenCore_OEM/CLASH_2_0.RAW
py2saber/OpenCore_OEM/CLASH_3_0.RAW
py2saber/OpenCore_OEM/CLASH_4_0.RAW
py2saber/OpenCore_OEM/CLASH_5_0.RAW
py2saber/OpenCore_OEM/CLASH_6_0.RAW
py2saber/OpenCore_OEM/CLASH_7_0.RAW
py2saber/OpenCore_OEM/CLASH_8_0.RAW
py2saber/OpenCore_OEM/CLASH_9_0.RAW
py2saber/OpenCore_OEM/HUM_0.RAW
py2saber/OpenCore_OEM/POWEROFF_0.RAW
py2saber/OpenCore_OEM/POWERON_0.RAW
py2saber/OpenCore_OEM/SMOOTHSWING.RAW
py2saber/OpenCore_OEM/SMOOTHSWINGH_1_0.RAW
py2saber/OpenCore_OEM/SMOOTHSWINGH_2_0.RAW
py2saber/OpenCore_OEM/SMOOTHSWINGH_3_0.RAW
py2saber/OpenCore_OEM/SMOOTHSWINGH_4_0.RAW
py2saber/OpenCore_OEM/SMOOTHSWINGH_5_0.RAW
py2saber/OpenCore_OEM/SMOOTHSWINGH_6_0.RAW
py2saber/OpenCore_OEM/SMOOTHSWINGH_7_0.RAW
py2saber/OpenCore_OEM/SMOOTHSWINGH_8_0.RAW
py2saber/OpenCore_OEM/SMOOTHSWINGL_1_0.RAW
py2saber/OpenCore_OEM/SMOOTHSWINGL_2_0.RAW
py2saber/OpenCore_OEM/SMOOTHSWINGL_3_0.RAW
py2saber/OpenCore_OEM/SMOOTHSWINGL_4_0.RAW
py2saber/OpenCore_OEM/SMOOTHSWINGL_5_0.RAW
py2saber/OpenCore_OEM/SMOOTHSWINGL_6_0.RAW
py2saber/OpenCore_OEM/SMOOTHSWINGL_7_0.RAW
py2saber/OpenCore_OEM/SMOOTHSWINGL_8_0.RAW
py2saber-0.19.5.dist-info/COPYING
py2saber-0.19.5.dist-info/METADATA
py2saber-0.19.5.dist-info/WHEEL
py2saber-0.19.5.dist-info/entry_points.txt
py2saber-0.19.5.dist-info/top_level.txt
py2saber-0.19.5.dist-info/RECORD
