Metadata-Version: 2.1
Name: py2saber
Version: 0.19.5
Summary: Python-based utility for OpenCore lightsabers
Author-email: Jason Ramboz <jramboz@gmail.com>
License:                     GNU GENERAL PUBLIC LICENSE
Project-URL: Homepage, https://github.com/jramboz/py2saber
Keywords: polaris,ludosport,lightsabers,opencore
Classifier: License :: OSI Approved :: GNU General Public License v3 (GPLv3)
Classifier: Programming Language :: Python
Classifier: Programming Language :: Python :: 3
Classifier: Development Status :: 4 - Beta
Requires-Python: >=3.9
License-File: COPYING
Requires-Dist: pyserial>=3.5
Requires-Dist: py-getch
Requires-Dist: aioserial
